xstavka_parse_package/__init__.py
xstavka_parse_package/parse.py
xstavka_parse_package-0.25.dist-info/METADATA
xstavka_parse_package-0.25.dist-info/WHEEL
xstavka_parse_package-0.25.dist-info/top_level.txt
xstavka_parse_package-0.25.dist-info/RECORD
