Metadata-Version: 2.1
Name: xstavka-parse-package
Version: 0.25
Summary: this unstable package
Home-page: UNKNOWN
Author: hackoff
License: UNKNOWN
Platform: UNKNOWN
Requires-Python: >=3.5
Requires-Dist: bs4
Requires-Dist: lxml
Requires-Dist: selenium
Requires-Dist: webdriver-manager
